setup.py
pywik/__init__.py
pywik.egg-info/PKG-INFO
pywik.egg-info/SOURCES.txt
pywik.egg-info/dependency_links.txt
pywik.egg-info/requires.txt
pywik.egg-info/top_level.txt