Metadata-Version: 1.0
Name: pywik
Version: 0.1
Summary: Python API for Piwik HTTP interface
Home-page: http://github.com/jrcamp/pywik
Author: Jay Camp
Author-email: jay.r.camp@gmail.com
License: UNKNOWN
Platform: UNKNOWN
